{"reference_导航栏.md":"CyGwev8t","reference_站点配置.md":"DuC9UqCp","reference_搜索.md":"EjEyp2Xw","reference_概览.md":"B0YyGq_b","reference_徽章.md":"COCzycVx","guide_路由.md":"DSMd7fYY","reference_侧边栏.md":"BUDBI-VY","reference_最后更新时间戳.md":"Cs17yedu","reference_布局.md":"CR6fZck2","guide_扩展默认主题.md":"DNaPm0hp","reference_团队页.md":"CfUA2BEh","guide_frontmatter.md":"xC4CLkme","guide_快速开始.md":"ESE0N27d","reference_frontmatter配置.md":"e9Vrpigi","reference_主页.md":"Co8LV5m7","reference_运行时api.md":"DTWW8okT","guide_链接cms.md":"LQZN9Oed","guide_构建时数据加载.md":"e4978Njz","reference_页脚.md":"CEOwrRZ9","api-examples.md":"3jKd6uxa","guide_mpa模式.md":"BsprJ7La","guide_自定义主题.md":"BHFodgCb","reference_carbon ads.md":"CTlOVqvB","guide_在markdown中使用vue.md":"DIMZ4E-t","guide_sitemap生成.md":"Be_cZsbg","reference_编辑链接.md":"CaJbsvp2","guide_markdown扩展.md":"Da5WvCmO","guide_什么是vitepress.md":"DFOSLCOA","index.md":"B-pxf7Hy","reference_上下页链接.md":"zq_XwqnE","guide_国际化.md":"CrII_dGl","reference_cli.md":"CqzsZGQQ","guide_ssr兼容性.md":"DGfuDtfu","guide_资源处理.md":"a1YccN9L","guide_部署.md":"DMNlR28p","markdown-examples.md":"ONC6UZgc"}
